{"sermons":[{"title":"My Lord, make this a secure land","date":{"iso8601":"2023-11-03T12:55:02+04:00","month":{"name":"November","shortname":"Nov","number":"11"},"day":{"name":"Friday","shortname":"Fri","number":"03"},"year":"2023"},"type":"friday","source":"uae-awqaf","editions":[{"language":"ar","format":"mp3","url":"https:\/\/cdn.islamic.network\/sermons\/uae-awqaf\/mp3\/2023-11-03-ar-My_Lord,_make_this_a_secure_land.mp3"},{"language":"en","format":"mp3","url":"https:\/\/cdn.islamic.network\/sermons\/uae-awqaf\/mp3\/2023-11-03-en-My_Lord,_make_this_a_secure_land.mp3"},{"language":"ur","format":"mp3","url":"https:\/\/cdn.islamic.network\/sermons\/uae-awqaf\/mp3\/2023-11-03-ur-My_Lord,_make_this_a_secure_land.mp3"},{"language":"en","format":"doc","url":"https:\/\/cdn.islamic.network\/sermons\/uae-awqaf\/doc\/2023-11-03-en-My_Lord,_make_this_a_secure_land.doc"},{"language":"en","format":"pdf","url":"https:\/\/cdn.islamic.network\/sermons\/uae-awqaf\/pdf\/2023-11-03-en-My_Lord,_make_this_a_secure_land.pdf"},{"language":"ur","format":"pdf","url":"https:\/\/cdn.islamic.network\/sermons\/uae-awqaf\/pdf\/2023-11-03-ur-My_Lord,_make_this_a_secure_land.pdf"}]},{"title":"Your Lord says: Call upon Me; I will respond to you","date":{"iso8601":"2023-11-10T12:55:02+04:00","month":{"name":"November","shortname":"Nov","number":"11"},"day":{"name":"Friday","shortname":"Fri","number":"10"},"year":"2023"},"type":"friday","source":"uae-awqaf","editions":[{"language":"ar","format":"mp3","url":"https:\/\/cdn.islamic.network\/sermons\/uae-awqaf\/mp3\/2023-11-10-ar-Your_Lord_says:_Call_upon_Me;_I_will_respond_to_you..mp3"},{"language":"en","format":"mp3","url":"https:\/\/cdn.islamic.network\/sermons\/uae-awqaf\/mp3\/2023-11-10-en-Your_Lord_says:_Call_upon_Me;_I_will_respond_to_you..mp3"},{"language":"ur","format":"mp3","url":"https:\/\/cdn.islamic.network\/sermons\/uae-awqaf\/mp3\/2023-11-10-ur-Your_Lord_says:_Call_upon_Me;_I_will_respond_to_you..mp3"},{"language":"en","format":"doc","url":"https:\/\/cdn.islamic.network\/sermons\/uae-awqaf\/doc\/2023-11-10-en-Your_Lord_says:_Call_upon_Me;_I_will_respond_to_you..doc"},{"language":"en","format":"pdf","url":"https:\/\/cdn.islamic.network\/sermons\/uae-awqaf\/pdf\/2023-11-10-en-Your_Lord_says:_Call_upon_Me;_I_will_respond_to_you..pdf"},{"language":"ur","format":"pdf","url":"https:\/\/cdn.islamic.network\/sermons\/uae-awqaf\/pdf\/2023-11-10-ur-Your_Lord_says:_Call_upon_Me;_I_will_respond_to_you..pdf"}]},{"title":"The Mother of the Believers, Zainab","date":{"iso8601":"2023-11-17T12:55:02+04:00","month":{"name":"November","shortname":"Nov","number":"11"},"day":{"name":"Friday","shortname":"Fri","number":"17"},"year":"2023"},"type":"friday","source":"uae-awqaf","editions":[{"language":"ar","format":"mp3","url":"https:\/\/cdn.islamic.network\/sermons\/uae-awqaf\/mp3\/2023-11-17-ar-The_Mother_of_the_Believers,_Zainab.mp3"},{"language":"en","format":"mp3","url":"https:\/\/cdn.islamic.network\/sermons\/uae-awqaf\/mp3\/2023-11-17-en-The_Mother_of_the_Believers,_Zainab.mp3"},{"language":"ur","format":"mp3","url":"https:\/\/cdn.islamic.network\/sermons\/uae-awqaf\/mp3\/2023-11-17-ur-The_Mother_of_the_Believers,_Zainab.mp3"},{"language":"en","format":"doc","url":"https:\/\/cdn.islamic.network\/sermons\/uae-awqaf\/doc\/2023-11-17-en-The_Mother_of_the_Believers,_Zainab.doc"},{"language":"en","format":"pdf","url":"https:\/\/cdn.islamic.network\/sermons\/uae-awqaf\/pdf\/2023-11-17-en-The_Mother_of_the_Believers,_Zainab.pdf"}]},{"title":"The Value of Giving","date":{"iso8601":"2023-11-24T12:55:02+04:00","month":{"name":"November","shortname":"Nov","number":"11"},"day":{"name":"Friday","shortname":"Fri","number":"24"},"year":"2023"},"type":"friday","source":"uae-awqaf","editions":[{"language":"ar","format":"mp3","url":"https:\/\/cdn.islamic.network\/sermons\/uae-awqaf\/mp3\/2023-11-24-ar-The_Value_of_Giving.mp3"},{"language":"en","format":"mp3","url":"https:\/\/cdn.islamic.network\/sermons\/uae-awqaf\/mp3\/2023-11-24-en-The_Value_of_Giving.mp3"},{"language":"ur","format":"mp3","url":"https:\/\/cdn.islamic.network\/sermons\/uae-awqaf\/mp3\/2023-11-24-ur-The_Value_of_Giving.mp3"},{"language":"en","format":"doc","url":"https:\/\/cdn.islamic.network\/sermons\/uae-awqaf\/doc\/2023-11-24-en-The_Value_of_Giving.doc"},{"language":"en","format":"pdf","url":"https:\/\/cdn.islamic.network\/sermons\/uae-awqaf\/pdf\/2023-11-24-en-The_Value_of_Giving.pdf"}]}],"month":{"name":"November","shortname":"Nov","number":"11"}}