[{"sermons":[{"title":"Allah charges no soul save to its capacity","date":{"iso8601":"2024-01-05T12:35:46+04:00","month":{"name":"January","shortname":"Jan","number":"01"},"day":{"name":"Friday","shortname":"Fri","number":"05"},"year":"2024"},"type":"friday","source":"uae-awqaf","editions":[{"language":"ar","format":"mp3","url":"https:\/\/cdn.islamic.network\/sermons\/uae-awqaf\/mp3\/2024-01-05-ar-Allah_charges_no_soul_save_to_its_capacity.mp3"},{"language":"en","format":"mp3","url":"https:\/\/cdn.islamic.network\/sermons\/uae-awqaf\/mp3\/2024-01-05-en-Allah_charges_no_soul_save_to_its_capacity.mp3"},{"language":"ur","format":"mp3","url":"https:\/\/cdn.islamic.network\/sermons\/uae-awqaf\/mp3\/2024-01-05-ur-Allah_charges_no_soul_save_to_its_capacity.mp3"},{"language":"en","format":"doc","url":"https:\/\/cdn.islamic.network\/sermons\/uae-awqaf\/doc\/2024-01-05-en-Allah_charges_no_soul_save_to_its_capacity.doc"},{"language":"en","format":"pdf","url":"https:\/\/cdn.islamic.network\/sermons\/uae-awqaf\/pdf\/2024-01-05-en-Allah_charges_no_soul_save_to_its_capacity.pdf"},{"language":"ur","format":"pdf","url":"https:\/\/cdn.islamic.network\/sermons\/uae-awqaf\/pdf\/2024-01-05-ur-Allah_charges_no_soul_save_to_its_capacity.pdf"}]},{"title":"Fulfilling our trust","date":{"iso8601":"2024-01-12T12:35:46+04:00","month":{"name":"January","shortname":"Jan","number":"01"},"day":{"name":"Friday","shortname":"Fri","number":"12"},"year":"2024"},"type":"friday","source":"uae-awqaf","editions":[{"language":"ar","format":"mp3","url":"https:\/\/cdn.islamic.network\/sermons\/uae-awqaf\/mp3\/2024-01-12-ar-Fulfilling_our_trust.mp3"},{"language":"en","format":"mp3","url":"https:\/\/cdn.islamic.network\/sermons\/uae-awqaf\/mp3\/2024-01-12-en-Fulfilling_our_trust.mp3"},{"language":"ur","format":"mp3","url":"https:\/\/cdn.islamic.network\/sermons\/uae-awqaf\/mp3\/2024-01-12-ur-Fulfilling_our_trust.mp3"},{"language":"en","format":"doc","url":"https:\/\/cdn.islamic.network\/sermons\/uae-awqaf\/doc\/2024-01-12-en-Fulfilling_our_trust.doc"},{"language":"en","format":"pdf","url":"https:\/\/cdn.islamic.network\/sermons\/uae-awqaf\/pdf\/2024-01-12-en-Fulfilling_our_trust.pdf"},{"language":"ur","format":"pdf","url":"https:\/\/cdn.islamic.network\/sermons\/uae-awqaf\/pdf\/2024-01-12-ur-Fulfilling_our_trust.pdf"}]},{"title":"Wisdom","date":{"iso8601":"2024-01-19T12:35:46+04:00","month":{"name":"January","shortname":"Jan","number":"01"},"day":{"name":"Friday","shortname":"Fri","number":"19"},"year":"2024"},"type":"friday","source":"uae-awqaf","editions":[{"language":"ar","format":"mp3","url":"https:\/\/cdn.islamic.network\/sermons\/uae-awqaf\/mp3\/2024-01-19-ar-Wisdom.mp3"},{"language":"en","format":"mp3","url":"https:\/\/cdn.islamic.network\/sermons\/uae-awqaf\/mp3\/2024-01-19-en-Wisdom.mp3"},{"language":"ur","format":"mp3","url":"https:\/\/cdn.islamic.network\/sermons\/uae-awqaf\/mp3\/2024-01-19-ur-Wisdom.mp3"},{"language":"ar","format":"doc","url":"https:\/\/cdn.islamic.network\/sermons\/uae-awqaf\/doc\/2024-01-19-ar-Wisdom.doc"},{"language":"en","format":"doc","url":"https:\/\/cdn.islamic.network\/sermons\/uae-awqaf\/doc\/2024-01-19-en-Wisdom.doc"},{"language":"ar","format":"pdf","url":"https:\/\/cdn.islamic.network\/sermons\/uae-awqaf\/pdf\/2024-01-19-ar-Wisdom.pdf"},{"language":"en","format":"pdf","url":"https:\/\/cdn.islamic.network\/sermons\/uae-awqaf\/pdf\/2024-01-19-en-Wisdom.pdf"}]},{"title":"The Sign of the Luminous Moon","date":{"iso8601":"2024-01-26T12:35:46+04:00","month":{"name":"January","shortname":"Jan","number":"01"},"day":{"name":"Friday","shortname":"Fri","number":"26"},"year":"2024"},"type":"friday","source":"uae-awqaf","editions":[{"language":"ar","format":"mp3","url":"https:\/\/cdn.islamic.network\/sermons\/uae-awqaf\/mp3\/2024-01-26-ar-The_Sign_of_the_Luminous_Moon.mp3"},{"language":"en","format":"mp3","url":"https:\/\/cdn.islamic.network\/sermons\/uae-awqaf\/mp3\/2024-01-26-en-The_Sign_of_the_Luminous_Moon.mp3"},{"language":"ur","format":"mp3","url":"https:\/\/cdn.islamic.network\/sermons\/uae-awqaf\/mp3\/2024-01-26-ur-The_Sign_of_the_Luminous_Moon.mp3"},{"language":"ar","format":"doc","url":"https:\/\/cdn.islamic.network\/sermons\/uae-awqaf\/doc\/2024-01-26-ar-The_Sign_of_the_Luminous_Moon.doc"},{"language":"en","format":"doc","url":"https:\/\/cdn.islamic.network\/sermons\/uae-awqaf\/doc\/2024-01-26-en-The_Sign_of_the_Luminous_Moon.doc"},{"language":"ar","format":"pdf","url":"https:\/\/cdn.islamic.network\/sermons\/uae-awqaf\/pdf\/2024-01-26-ar-The_Sign_of_the_Luminous_Moon.pdf"},{"language":"en","format":"pdf","url":"https:\/\/cdn.islamic.network\/sermons\/uae-awqaf\/pdf\/2024-01-26-en-The_Sign_of_the_Luminous_Moon.pdf"},{"language":"ur","format":"pdf","url":"https:\/\/cdn.islamic.network\/sermons\/uae-awqaf\/pdf\/2024-01-26-ur-The_Sign_of_the_Luminous_Moon.pdf"}]}],"month":{"name":"January","shortname":"Jan","number":"01"}}]